AUTHORS.rst
CONTRIBUTING.rst
HISTORY.rst
LICENSE
MANIFEST.in
README.rst
setup.cfg
setup.py
docs/Makefile
docs/authors.rst
docs/conf.py
docs/contributing.rst
docs/history.rst
docs/index.rst
docs/installation.rst
docs/make.bat
docs/modules.rst
docs/pyJaya.rst
docs/pyJaya.variants.rst
docs/readme.rst
docs/usage.rst
docs/_build/html/_static/file.png
docs/_build/html/_static/minus.png
docs/_build/html/_static/plus.png
docs/_build/latex/Makefile
docs/_build/latex/make.bat
pyJaya/__init__.py
pyJaya/consts.py
pyJaya/population.py
pyJaya/solution.py
pyJaya/variables.py
pyJaya.egg-info/PKG-INFO
pyJaya.egg-info/SOURCES.txt
pyJaya.egg-info/dependency_links.txt
pyJaya.egg-info/not-zip-safe
pyJaya.egg-info/requires.txt
pyJaya.egg-info/top_level.txt
pyJaya/variants/__init__.py
pyJaya/variants/base.py
pyJaya/variants/binary.py
pyJaya/variants/clasic.py
pyJaya/variants/quasiOppositional.py
pyJaya/variants/samp.py
pyJaya/variants/sampe.py
pyJaya/variants/selfAdaptive.py
tests/__init__.py
tests/test_JayaClasic.py