Metadata-Version: 1.2
Name: pyJaya
Version: 0.1.8
Summary: Python implementation of Jaya Algorithm and its variants
Home-page: https://github.com/eadomenech/pyJaya
Author: Ernesto Avila-Domenech
Author-email: eadomenech@gmail.com
License: MIT license
Keywords: pyJaya
Platform: UNKNOWN
Classifier: Development Status :: 2 - Pre-Alpha
Classifier: Intended Audience :: Developers
Classifier: License :: OSI Approved :: MIT License
Classifier: Natural Language :: English
Classifier: Programming Language :: Python :: 3
Classifier: Programming Language :: Python :: 3.5
Classifier: Programming Language :: Python :: 3.6
Classifier: Programming Language :: Python :: 3.7
Classifier: Programming Language :: Python :: 3.8
Requires-Python: >=3.5
